fstrings.py
fstrings-0.1.0.dist-info/DESCRIPTION.rst
fstrings-0.1.0.dist-info/METADATA
fstrings-0.1.0.dist-info/RECORD
fstrings-0.1.0.dist-info/WHEEL
fstrings-0.1.0.dist-info/metadata.json
fstrings-0.1.0.dist-info/top_level.txt
