Metadata-Version: 1.1
Name: fstrings
Version: 0.1.0
Summary: 
